stocksent/__init__.py
stocksent/get_sentiment_data.py
stocksent/sentiment.py
stocksent/stock_list.txt
stocksent-0.3.0.dist-info/LICENSE
stocksent-0.3.0.dist-info/METADATA
stocksent-0.3.0.dist-info/WHEEL
stocksent-0.3.0.dist-info/top_level.txt
stocksent-0.3.0.dist-info/RECORD
