Metadata-Version: 2.1
Name: stocksent
Version: 0.3.0
Summary: A Python library for sentiment analysis of various tickers from the latest news by trusted sources, and tools to plot results.
Home-page: https://stocksent.readthedocs.io/
Author: Arya Manjaramkar
Author-email: aryagm01@email.com
License: Mozilla Public License 2.0
Platform: UNKNOWN
Classifier: License :: OSI Approved :: Mozilla Public License 2.0 (MPL 2.0)
Classifier: Natural Language :: English
Classifier: Topic :: Software Development :: Libraries :: Python Modules
Classifier: Programming Language :: Python
Classifier: Programming Language :: Python :: 3
Classifier: Programming Language :: Python :: 3.6
Classifier: Programming Language :: Python :: 3.7
Classifier: Programming Language :: Python :: 3.8
Classifier: Programming Language :: Python :: 3.9
Classifier: Operating System :: OS Independent
Requires-Dist: numpy
Requires-Dist: matplotlib
Requires-Dist: pandas
Requires-Dist: nltk
Requires-Dist: wordcloud
Requires-Dist: bs4
